Workbook

Sheet 📋 Budgets
A1: Category | B1: Monthly Budget
A2: Food & Dining | B2: 0
A3: Gas & Fuel | B3: 0
A4: Groceries | B4: 0
A5: Shopping | B5: 0
A6: Subscriptions | B6: 0
A7: Entertainment | B7: 0
A8: Healthcare | B8: 0
A9: Utilities | B9: 0
A10: Travel | B10: 0
A11: Other | B11: 0

Sheet 📊 Dashboard
A1: Year Summary | F1: Budget Progress | K1: Viewing month: | L1: Jan 2026
A2: Month | B2: Expenses | C2: Income | D2: Net | F2: Category | G2: Spent | H2: Budget | I2: % Used
A3: Jan 2026 | B3: =IFERROR(INDIRECT("'"&A3&"'!I3"),0) | C3: =IFERROR(INDIRECT("'"&A3&"'!I2"),0) | D3: =C3-B3 | F3: Food & Dining | G3: =IFERROR(SUMIF(INDIRECT("'"&$L$1&"'!H:H"),F3,INDIRECT("'"&$L$1&"'!I:I")),0) | H3: =IFERROR(VLOOKUP(F3,'📋 Budgets'!A:B,2,0),0) | I3: =IFERROR(ABS(G3)/H3,0)
A4: Feb 2026 | B4: =IFERROR(INDIRECT("'"&A4&"'!I3"),0) | C4: =IFERROR(INDIRECT("'"&A4&"'!I2"),0) | D4: =C4-B4 | F4: Gas & Fuel | G4: =IFERROR(SUMIF(INDIRECT("'"&$L$1&"'!H:H"),F4,INDIRECT("'"&$L$1&"'!I:I")),0) | H4: =IFERROR(VLOOKUP(F4,'📋 Budgets'!A:B,2,0),0) | I4: =IFERROR(ABS(G4)/H4,0)
A5: Mar 2026 | B5: =IFERROR(INDIRECT("'"&A5&"'!I3"),0) | C5: =IFERROR(INDIRECT("'"&A5&"'!I2"),0) | D5: =C5-B5 | F5: Groceries | G5: =IFERROR(SUMIF(INDIRECT("'"&$L$1&"'!H:H"),F5,INDIRECT("'"&$L$1&"'!I:I")),0) | H5: =IFERROR(VLOOKUP(F5,'📋 Budgets'!A:B,2,0),0) | I5: =IFERROR(ABS(G5)/H5,0)
A6: Apr 2026 | B6: =IFERROR(INDIRECT("'"&A6&"'!I3"),0) | C6: =IFERROR(INDIRECT("'"&A6&"'!I2"),0) | D6: =C6-B6 | F6: Shopping | G6: =IFERROR(SUMIF(INDIRECT("'"&$L$1&"'!H:H"),F6,INDIRECT("'"&$L$1&"'!I:I")),0) | H6: =IFERROR(VLOOKUP(F6,'📋 Budgets'!A:B,2,0),0) | I6: =IFERROR(ABS(G6)/H6,0)
A7: May 2026 | B7: =IFERROR(INDIRECT("'"&A7&"'!I3"),0) | C7: =IFERROR(INDIRECT("'"&A7&"'!I2"),0) | D7: =C7-B7 | F7: Subscriptions | G7: =IFERROR(SUMIF(INDIRECT("'"&$L$1&"'!H:H"),F7,INDIRECT("'"&$L$1&"'!I:I")),0) | H7: =IFERROR(VLOOKUP(F7,'📋 Budgets'!A:B,2,0),0) | I7: =IFERROR(ABS(G7)/H7,0)
A8: Jun 2026 | B8: =IFERROR(INDIRECT("'"&A8&"'!I3"),0) | C8: =IFERROR(INDIRECT("'"&A8&"'!I2"),0) | D8: =C8-B8 | F8: Entertainment | G8: =IFERROR(SUMIF(INDIRECT("'"&$L$1&"'!H:H"),F8,INDIRECT("'"&$L$1&"'!I:I")),0) | H8: =IFERROR(VLOOKUP(F8,'📋 Budgets'!A:B,2,0),0) | I8: =IFERROR(ABS(G8)/H8,0)
A9: Jul 2026 | B9: =IFERROR(INDIRECT("'"&A9&"'!I3"),0) | C9: =IFERROR(INDIRECT("'"&A9&"'!I2"),0) | D9: =C9-B9 | F9: Healthcare | G9: =IFERROR(SUMIF(INDIRECT("'"&$L$1&"'!H:H"),F9,INDIRECT("'"&$L$1&"'!I:I")),0) | H9: =IFERROR(VLOOKUP(F9,'📋 Budgets'!A:B,2,0),0) | I9: =IFERROR(ABS(G9)/H9,0)
A10: Aug 2026 | B10: =IFERROR(INDIRECT("'"&A10&"'!I3"),0) | C10: =IFERROR(INDIRECT("'"&A10&"'!I2"),0) | D10: =C10-B10 | F10: Utilities | G10: =IFERROR(SUMIF(INDIRECT("'"&$L$1&"'!H:H"),F10,INDIRECT("'"&$L$1&"'!I:I")),0) | H10: =IFERROR(VLOOKUP(F10,'📋 Budgets'!A:B,2,0),0) | I10: =IFERROR(ABS(G10)/H10,0)
A11: Sep 2026 | B11: =IFERROR(INDIRECT("'"&A11&"'!I3"),0) | C11: =IFERROR(INDIRECT("'"&A11&"'!I2"),0) | D11: =C11-B11 | F11: Travel | G11: =IFERROR(SUMIF(INDIRECT("'"&$L$1&"'!H:H"),F11,INDIRECT("'"&$L$1&"'!I:I")),0) | H11: =IFERROR(VLOOKUP(F11,'📋 Budgets'!A:B,2,0),0) | I11: =IFERROR(ABS(G11)/H11,0)
A12: Oct 2026 | B12: =IFERROR(INDIRECT("'"&A12&"'!I3"),0) | C12: =IFERROR(INDIRECT("'"&A12&"'!I2"),0) | D12: =C12-B12 | F12: Other | G12: =IFERROR(SUMIF(INDIRECT("'"&$L$1&"'!H:H"),F12,INDIRECT("'"&$L$1&"'!I:I")),0) | H12: =IFERROR(VLOOKUP(F12,'📋 Budgets'!A:B,2,0),0) | I12: =IFERROR(ABS(G12)/H12,0)
A13: Nov 2026 | B13: =IFERROR(INDIRECT("'"&A13&"'!I3"),0) | C13: =IFERROR(INDIRECT("'"&A13&"'!I2"),0) | D13: =C13-B13
A14: Dec 2026 | B14: =IFERROR(INDIRECT("'"&A14&"'!I3"),0) | C14: =IFERROR(INDIRECT("'"&A14&"'!I2"),0) | D14: =C14-B14

Sheet _template
A1: Date | B1: Description | C1: Amount | D1: Category | E1: Type | H1: 📊 Monthly Summary
H2: Total Income | I2: =SUMIF(E:E,"Income",C:C)
H3: Total Expenses | I3: =SUMIF(E:E,"Expense",C:C)
H4: Net Balance | I4: =I2-I3
H5: Uncategorized | I5: =COUNTIF(D:D,"Uncategorized")
H7: Category | I7: Subtotal
H8: Food & Dining | I8: =SUMIF(D:D,"Food & Dining",C:C)
H9: Gas & Fuel | I9: =SUMIF(D:D,"Gas & Fuel",C:C)
H10: Groceries | I10: =SUMIF(D:D,"Groceries",C:C)
H11: Shopping | I11: =SUMIF(D:D,"Shopping",C:C)
H12: Subscriptions | I12: =SUMIF(D:D,"Subscriptions",C:C)
H13: Entertainment | I13: =SUMIF(D:D,"Entertainment",C:C)
H14: Healthcare | I14: =SUMIF(D:D,"Healthcare",C:C)
H15: Utilities | I15: =SUMIF(D:D,"Utilities",C:C)
H16: Travel | I16: =SUMIF(D:D,"Travel",C:C)
H17: Other | I17: =SUMIF(D:D,"Other",C:C)

Sheet Jan 2026
A1: Date | B1: Description | C1: Amount | D1: Category | E1: Type | H1: 📊 Monthly Summary
H2: Total Income | I2: =SUMIF(E:E,"Income",C:C)
H3: Total Expenses | I3: =SUMIF(E:E,"Expense",C:C)
H4: Net Balance | I4: =I2-I3
H5: Uncategorized | I5: =COUNTIF(D:D,"Uncategorized")
H7: Category | I7: Subtotal
H8: Food & Dining | I8: =SUMIF(D:D,"Food & Dining",C:C)
H9: Gas & Fuel | I9: =SUMIF(D:D,"Gas & Fuel",C:C)
H10: Groceries | I10: =SUMIF(D:D,"Groceries",C:C)
H11: Shopping | I11: =SUMIF(D:D,"Shopping",C:C)
H12: Subscriptions | I12: =SUMIF(D:D,"Subscriptions",C:C)
H13: Entertainment | I13: =SUMIF(D:D,"Entertainment",C:C)
H14: Healthcare | I14: =SUMIF(D:D,"Healthcare",C:C)
H15: Utilities | I15: =SUMIF(D:D,"Utilities",C:C)
H16: Travel | I16: =SUMIF(D:D,"Travel",C:C)
H17: Other | I17: =SUMIF(D:D,"Other",C:C)
